mycms/__init__.py
mycms/addsbygoogle.py
mycms/admin.py
mycms/api.py
mycms/cmsentries_text.txt
mycms/exceptions.py
mycms/fields.py
mycms/funclib.py
mycms/models.py
mycms/response.py
mycms/search_indexes.py
mycms/serializers.py
mycms/sitemap.py
mycms/urls.py
mycms/utils.py
mycms/views.py
mycms/widgits.py
mycms/wingdbstub.py
mycms/assets/__init__.py
mycms/creole/__init__.py
mycms/creole/cmdline.py
mycms/creole/exceptions.py
mycms/creole/py3compat.py
mycms/creole/setup_utils.py
mycms/creole/creole2html/__init__.py
mycms/creole/creole2html/emitter.py
mycms/creole/creole2html/parser.py
mycms/creole/creole2html/rules.py
mycms/creole/html_parser/__init__.py
mycms/creole/html_parser/config.py
mycms/creole/html_parser/parser.py
mycms/creole/html_tools/__init__.py
mycms/creole/html_tools/deentity.py
mycms/creole/html_tools/strip_html.py
mycms/creole/html_tools/text_tools.py
mycms/creole/rest2html/__init__.py
mycms/creole/rest2html/clean_writer.py
mycms/creole/rest2html/pypi_rest2html.py
mycms/creole/shared/HTMLParsercompat.py
mycms/creole/shared/__init__.py
mycms/creole/shared/base_emitter.py
mycms/creole/shared/document_tree.py
mycms/creole/shared/example_macros.py
mycms/creole/shared/html_parser.py
mycms/creole/shared/markup_table.py
mycms/creole/shared/unknown_tags.py
mycms/creole/shared/utils.py
mycms/management/__init__.py
mycms/management/commands/__init__.py
mycms/management/commands/addsuperuser.py
mycms/management/commands/compile_dustjs.py
mycms/management/commands/live_tests.py
mycms/management/commands/sandbox.py
mycms/management/commands/tests.py
mycms/management/commands/tests_classes/__init__.py
mycms/management/commands/tests_classes/category_page_tests.py
mycms/migrations/0001_initial.py
mycms/migrations/0002_cmsarchivesindex.py
mycms/migrations/0003_cmsentries_lists_include.py
mycms/migrations/0004_cmsentries_logo_url.py
mycms/migrations/__init__.py
mycms/static/assets/category_editor.html/FedoraSilverBlue-2019-02-18-11-26-22.png
mycms-0.1.9.dist-info/AUTHORS.txt
mycms-0.1.9.dist-info/LICENSE.txt
mycms-0.1.9.dist-info/METADATA
mycms-0.1.9.dist-info/WHEEL
mycms-0.1.9.dist-info/top_level.txt
mycms-0.1.9.dist-info/RECORD
